private_cw_rpa/__init__.py
private_cw_rpa/libraries/__init__.py
private_cw_rpa/libraries/cloud/__init__.py
private_cw_rpa/libraries/cloud/pre_defined_functions.py
private_cw_rpa/libraries/common/__init__.py
private_cw_rpa/libraries/common/common_functions.py
private_cw_rpa/libraries/device/__init__.py
private_cw_rpa/libraries/device/execute_powershell_script.py
private_cw_rpa-0.1.4.dist-info/LICENSE
private_cw_rpa-0.1.4.dist-info/METADATA
private_cw_rpa-0.1.4.dist-info/WHEEL
private_cw_rpa-0.1.4.dist-info/top_level.txt
private_cw_rpa-0.1.4.dist-info/RECORD
